{
  "problem_id": "hint_949",
  "domain": "precalculus",
  "type": "Precalculus",
  "level": "Level 4",
  "problem": "Find all $a,$ $0^\\circ < a < 360^\\circ,$ such that $\\cos a,$ $\\cos 2a,$ and $\\cos 3a$ form an arithmetic sequence, in that order.  Enter the solutions, separated by commas, in degrees.",
  "n_questions": 8,
  "labels": [
    "f",
    "f",
    "r",
    "b",
    "b",
    "b",
    "b",
    "r"
  ],
  "classified_questions": [
    {
      "index": 1,
      "question": "What is the given equation we need to solve, and what are the conditions for the variable a?",
      "label": "f",
      "label_name": "feature-pointing"
    },
    {
      "index": 2,
      "question": "How can we represent the equation using trigonometric functions?",
      "label": "f",
      "label_name": "feature-pointing"
    },
    {
      "index": 3,
      "question": "What do we know about the arithmetic sequence formed by the cosine values?",
      "label": "r",
      "label_name": "principle-stating"
    },
    {
      "index": 4,
      "question": "How can we simplify the equation using the double-angle and triple-angle formulas?",
      "label": "b",
      "label_name": "bottom-out"
    },
    {
      "index": 5,
      "question": "Can we factor the simplified equation? If so, what are the resulting expressions?",
      "label": "b",
      "label_name": "bottom-out"
    },
    {
      "index": 6,
      "question": "What are the possible values for cos a that satisfy the factored equation?",
      "label": "b",
      "label_name": "bottom-out"
    },
    {
      "index": 7,
      "question": "How can we find the corresponding values of a, taking into account the given conditions?",
      "label": "b",
      "label_name": "bottom-out"
    },
    {
      "index": 8,
      "question": "What are the solutions for a within the given range?",
      "label": "r",
      "label_name": "principle-stating"
    }
  ]
}