{
  "problem_id": "hint_262",
  "domain": "number_theory",
  "type": "Number Theory",
  "level": "Level 4",
  "problem_type": "FP",
  "problem_type_name": "First Pieces",
  "problem": "How many positive three-digit integers with a $5$ in the units place are divisible by $15$?",
  "n_questions": 6,
  "labels": [
    "f",
    "r",
    "b",
    "b",
    "b",
    "e"
  ],
  "classified_questions": [
    {
      "index": 1,
      "question": "What is the range of three-digit multiples of 15?",
      "label": "f",
      "label_name": "feature-pointing"
    },
    {
      "index": 2,
      "question": "What is the relationship between multiples of 5 and multiples of 15?",
      "label": "r",
      "label_name": "principle-stating"
    },
    {
      "index": 3,
      "question": "How many of the three-digit multiples of 15 are odd?",
      "label": "b",
      "label_name": "bottom-out"
    },
    {
      "index": 4,
      "question": "How did you calculate the number of odd, three-digit multiples of 15?",
      "label": "b",
      "label_name": "bottom-out"
    },
    {
      "index": 5,
      "question": "How many positive, three-digit integers with a 5 in the units place are divisible by 15?",
      "label": "b",
      "label_name": "bottom-out"
    },
    {
      "index": 6,
      "question": "Can you think of another way to approach this problem?",
      "label": "e",
      "label_name": "extension"
    }
  ]
}