{
  "problem_id": "hint_460",
  "domain": "algebra",
  "type": "Algebra",
  "level": "Level 3",
  "problem": "Let \\[f(x) = \\left\\{\n\\begin{array}{cl}\nax+3 & \\text{ if }x>0, \\\\\nab & \\text{ if }x=0, \\\\\nbx+c & \\text{ if }x<0.\n\\end{array}\n\\right.\\]If $f(2)=5$, $f(0)=5$, and $f(-2)=-10$, and $a$, $b$, and $c$ are nonnegative integers, then what is $a+b+c$?",
  "n_questions": 9,
  "labels": [
    "b",
    "b",
    "b",
    "b",
    "b",
    "b",
    "b",
    "b",
    "b"
  ],
  "classified_questions": [
    {
      "index": 1,
      "question": "Can you describe what the function f(x) represents and how it is defined for different values of x?",
      "label": "b",
      "label_name": "bottom-out"
    },
    {
      "index": 2,
      "question": "Based on the given information, what can you infer about the value of f(x) when x > 0?",
      "label": "b",
      "label_name": "bottom-out"
    },
    {
      "index": 3,
      "question": "What can you conclude about the value of f(x) when x = 0 based on the given information?",
      "label": "b",
      "label_name": "bottom-out"
    },
    {
      "index": 4,
      "question": "Based on the given information, what can you deduce about the value of f(x) when x < 0?",
      "label": "b",
      "label_name": "bottom-out"
    },
    {
      "index": 5,
      "question": "With the information f(2) = 5, f(0) = 5, and f(-2) = -10, can you derive any equations or conditions involving a, b, and c?",
      "label": "b",
      "label_name": "bottom-out"
    },
    {
      "index": 6,
      "question": "How can you use the information from the previous question to determine the values of a, b, and c?",
      "label": "b",
      "label_name": "bottom-out"
    },
    {
      "index": 7,
      "question": "Considering that a, b, and c are nonnegative integers, what possibilities exist for the values of a, b, and c?",
      "label": "b",
      "label_name": "bottom-out"
    },
    {
      "index": 8,
      "question": "Can you narrow down the possible values of a, b, and c further using the given information and the constraints on a, b, and c?",
      "label": "b",
      "label_name": "bottom-out"
    },
    {
      "index": 9,
      "question": "What is the final value of a + b + c based on your deductions and reasoning?",
      "label": "b",
      "label_name": "bottom-out"
    }
  ]
}