{
  "problem_id": "hint_1027",
  "domain": "counting_and_probability",
  "type": "Counting & Probability",
  "level": "Level 4",
  "problem_type": "IN",
  "problem_type_name": "Interpretations",
  "problem": "How many 9 step paths are there from $E$ to $G$ which pass through $F$?[asy]size(4cm,4cm);int w=6;int h=5;int i;pen p=fontsize(9);for (i=0; i<h; ++i){draw((0,i) -- (w-1,i));}for (i=0; i<w; ++i){draw((i, 0)--(i,h-1));}label(\"G\", (w-1,0), SE, p);label(\"E\", (0,h-1), NW, p);label(\"F\", (3,3), NE, p);[/asy]",
  "n_questions": 7,
  "labels": [
    "f",
    "b",
    "b",
    "b",
    "b",
    "b",
    "b"
  ],
  "classified_questions": [
    {
      "index": 1,
      "question": "What is the problem asking us to find?",
      "label": "f",
      "label_name": "feature-pointing"
    },
    {
      "index": 2,
      "question": "How many steps are there from $E$ to $F$? How many steps are there from $F$ to $G$?",
      "label": "b",
      "label_name": "bottom-out"
    },
    {
      "index": 3,
      "question": "How many different paths are there from $E$ to $F$? How did you arrive at this answer?",
      "label": "b",
      "label_name": "bottom-out"
    },
    {
      "index": 4,
      "question": "How many different paths are there from $F$ to $G$? How did you arrive at this answer?",
      "label": "b",
      "label_name": "bottom-out"
    },
    {
      "index": 5,
      "question": "How can you combine the number of paths from $E$ to $F$ and from $F$ to $G$ to get the total number of paths from $E$ to $G$ that pass through $F$?",
      "label": "b",
      "label_name": "bottom-out"
    },
    {
      "index": 6,
      "question": "Can you think of a general formula to calculate the number of paths from one point to another on an $n \\times m$ grid?",
      "label": "b",
      "label_name": "bottom-out"
    },
    {
      "index": 7,
      "question": "What if we were asked to find the number of paths from $E$ to $G$ that do not pass through $F$? How could we approach this problem?",
      "label": "b",
      "label_name": "bottom-out"
    }
  ]
}